efficientvit/__init__.py
efficientvit/cls_model_zoo.py
efficientvit/sam_model_zoo.py
efficientvit/seg_model_zoo.py
efficientvit/version.py
efficientvit/apps/__init__.py
efficientvit/apps/setup.py
efficientvit/apps/data_provider/__init__.py
efficientvit/apps/data_provider/base.py
efficientvit/apps/data_provider/augment/__init__.py
efficientvit/apps/data_provider/augment/bbox.py
efficientvit/apps/data_provider/augment/color_aug.py
efficientvit/apps/data_provider/random_resolution/__init__.py
efficientvit/apps/data_provider/random_resolution/_data_loader.py
efficientvit/apps/data_provider/random_resolution/_data_worker.py
efficientvit/apps/data_provider/random_resolution/controller.py
efficientvit/apps/trainer/__init__.py
efficientvit/apps/trainer/base.py
efficientvit/apps/trainer/run_config.py
efficientvit/apps/utils/__init__.py
efficientvit/apps/utils/dist.py
efficientvit/apps/utils/ema.py
efficientvit/apps/utils/export.py
efficientvit/apps/utils/init.py
efficientvit/apps/utils/lr.py
efficientvit/apps/utils/metric.py
efficientvit/apps/utils/misc.py
efficientvit/apps/utils/opt.py
efficientvit/clscore/__init__.py
efficientvit/clscore/data_provider/__init__.py
efficientvit/clscore/data_provider/imagenet.py
efficientvit/clscore/trainer/__init__.py
efficientvit/clscore/trainer/cls_run_config.py
efficientvit/clscore/trainer/cls_trainer.py
efficientvit/clscore/trainer/utils/__init__.py
efficientvit/clscore/trainer/utils/label_smooth.py
efficientvit/clscore/trainer/utils/metric.py
efficientvit/clscore/trainer/utils/mixup.py
efficientvit/models/__init__.py
efficientvit/models/efficientvit/__init__.py
efficientvit/models/efficientvit/backbone.py
efficientvit/models/efficientvit/cls.py
efficientvit/models/efficientvit/sam.py
efficientvit/models/efficientvit/seg.py
efficientvit/models/nn/__init__.py
efficientvit/models/nn/act.py
efficientvit/models/nn/drop.py
efficientvit/models/nn/norm.py
efficientvit/models/nn/ops.py
efficientvit/models/utils/__init__.py
efficientvit_gml-0.1.10.dist-info/LICENSE
efficientvit_gml-0.1.10.dist-info/METADATA
efficientvit_gml-0.1.10.dist-info/WHEEL
efficientvit_gml-0.1.10.dist-info/top_level.txt
efficientvit_gml-0.1.10.dist-info/RECORD
