Metadata-Version: 2.1
Name: efficientvit-gml
Version: 0.1.10
Summary: open-set object detector
Home-page: https://github.com/mit-han-lab/efficientvit
License: Apache License
License-File: LICENSE
Requires-Dist: torch
Requires-Dist: torchvision
Requires-Dist: einops
Requires-Dist: opencv-python-headless
Requires-Dist: timm
Requires-Dist: tqdm
Requires-Dist: torchprofile
Requires-Dist: matplotlib
Requires-Dist: transformers
Requires-Dist: onnx
Requires-Dist: onnxsim
Requires-Dist: onnxruntime
Requires-Dist: pycocotools
Requires-Dist: segment-anything-py
